package com.tonic.utill;

import lombok.Getter;

/**
 * Enum representing all JVM opcodes as per Java 11 Specification.
 */
@Getter
public enum Opcode {
    NOP(0x00, "nop", 0),
    ACONST_NULL(0x01, "aconst_null", 0),
    ICONST_M1(0x02, "iconst_m1", 0),
    ICONST_0(0x03, "iconst_0", 0),
    ICONST_1(0x04, "iconst_1", 0),
    ICONST_2(0x05, "iconst_2", 0),
    ICONST_3(0x06, "iconst_3", 0),
    ICONST_4(0x07, "iconst_4", 0),
    ICONST_5(0x08, "iconst_5", 0),
    LCONST_0(0x09, "lconst_0", 0),
    LCONST_1(0x0A, "lconst_1", 0),
    FCONST_0(0x0B, "fconst_0", 0),
    FCONST_1(0x0C, "fconst_1", 0),
    FCONST_2(0x0D, "fconst_2", 0),
    DCONST_0(0x0E, "dconst_0", 0),
    DCONST_1(0x0F, "dconst_1", 0),
    BIPUSH(0x10, "bipush", 1),
    SIPUSH(0x11, "sipush", 2),
    LDC(0x12, "ldc", 1),
    LDC_W(0x13, "ldc_w", 2),
    LDC2_W(0x14, "ldc2_w", 2),
    ILOAD(0x15, "iload", 1),
    LLOAD(0x16, "lload", 1),
    FLOAD(0x17, "fload", 1),
    DLOAD(0x18, "dload", 1),
    ALOAD(0x19, "aload", 1),
    ILOAD_0(0x1A, "iload_0", 0),
    ILOAD_1(0x1B, "iload_1", 0),
    ILOAD_2(0x1C, "iload_2", 0),
    ILOAD_3(0x1D, "iload_3", 0),
    LLOAD_0(0x1E, "lload_0", 0),
    LLOAD_1(0x1F, "lload_1", 0),
    LLOAD_2(0x20, "lload_2", 0),
    LLOAD_3(0x21, "lload_3", 0),
    FLOAD_0(0x22, "fload_0", 0),
    FLOAD_1(0x23, "fload_1", 0),
    FLOAD_2(0x24, "fload_2", 0),
    FLOAD_3(0x25, "fload_3", 0),
    DLOAD_0(0x26, "dload_0", 0),
    DLOAD_1(0x27, "dload_1", 0),
    DLOAD_2(0x28, "dload_2", 0),
    DLOAD_3(0x29, "dload_3", 0),
    ALOAD_0(0x2A, "aload_0", 0),
    ALOAD_1(0x2B, "aload_1", 0),
    ALOAD_2(0x2C, "aload_2", 0),
    ALOAD_3(0x2D, "aload_3", 0),
    IALOAD(0x2E, "iaload", 0),
    LALOAD(0x2F, "laload", 0),
    FALOAD(0x30, "faload", 0),
    DALOAD(0x31, "daload", 0),
    AALOAD(0x32, "aaload", 0),
    BALOAD(0x33, "baload", 0),
    CALOAD(0x34, "caload", 0),
    SALOAD(0x35, "saload", 0),
    ISTORE(0x36, "istore", 1),
    LSTORE(0x37, "lstore", 1),
    FSTORE(0x38, "fstore", 1),
    DSTORE(0x39, "dstore", 1),
    ASTORE(0x3A, "astore", 1),
    ISTORE_0(0x3B, "istore_0", 0),
    ISTORE_1(0x3C, "istore_1", 0),
    ISTORE_2(0x3D, "istore_2", 0),
    ISTORE_3(0x3E, "istore_3", 0),
    LSTORE_0(0x3F, "lstore_0", 0),
    LSTORE_1(0x40, "lstore_1", 0),
    LSTORE_2(0x41, "lstore_2", 0),
    LSTORE_3(0x42, "lstore_3", 0),
    FSTORE_0(0x43, "fstore_0", 0),
    FSTORE_1(0x44, "fstore_1", 0),
    FSTORE_2(0x45, "fstore_2", 0),
    FSTORE_3(0x46, "fstore_3", 0),
    DSTORE_0(0x47, "dstore_0", 0),
    DSTORE_1(0x48, "dstore_1", 0),
    DSTORE_2(0x49, "dstore_2", 0),
    DSTORE_3(0x4A, "dstore_3", 0),
    ASTORE_0(0x4B, "astore_0", 0),
    ASTORE_1(0x4C, "astore_1", 0),
    ASTORE_2(0x4D, "astore_2", 0),
    ASTORE_3(0x4E, "astore_3", 0),
    IASTORE(0x4F, "iastore", 0),
    LASTORE(0x50, "lastore", 0),
    FASTORE(0x51, "fastore", 0),
    DASTORE(0x52, "dastore", 0),
    AASTORE(0x53, "aastore", 0),
    BASTORE(0x54, "bastore", 0),
    CASTORE(0x55, "castore", 0),
    SASTORE(0x56, "sastore", 0),
    POP(0x57, "pop", 0),
    POP2(0x58, "pop2", 0),
    DUP(0x59, "dup", 0),
    DUP_X1(0x5A, "dup_x1", 0),
    DUP_X2(0x5B, "dup_x2", 0),
    DUP2(0x5C, "dup2", 0),
    DUP2_X1(0x5D, "dup2_x1", 0),
    DUP2_X2(0x5E, "dup2_x2", 0),
    SWAP(0x5F, "swap", 0),
    IADD(0x60, "iadd", 0),
    LADD(0x61, "ladd", 0),
    FADD(0x62, "fadd", 0),
    DADD(0x63, "dadd", 0),
    ISUB(0x64, "isub", 0),
    LSUB(0x65, "lsub", 0),
    FSUB(0x66, "fsub", 0),
    DSUB(0x67, "dsub", 0),
    IMUL(0x68, "imul", 0),
    LMUL(0x69, "lmul", 0),
    FMUL(0x6A, "fmul", 0),
    DMUL(0x6B, "dmul", 0),
    IDIV(0x6C, "idiv", 0),
    LDIV(0x6D, "ldiv", 0),
    FDIV(0x6E, "fdiv", 0),
    DDIV(0x6F, "ddiv", 0),
    IREM(0x70, "irem", 0),
    LREM(0x71, "lrem", 0),
    FREM(0x72, "frem", 0),
    DREM(0x73, "drem", 0),
    INEG(0x74, "ineg", 0),
    LNEG(0x75, "lneg", 0),
    FNEG(0x76, "fneg", 0),
    DNEG(0x77, "dneg", 0),
    ISHL(0x78, "ishl", 0),
    LSHL(0x79, "lshl", 0),
    ISHR(0x7A, "ishr", 0),
    LSHR(0x7B, "lshr", 0),
    IUSHR(0x7C, "iushr", 0),
    LUSHR(0x7D, "lushr", 0),
    IAND(0x7E, "iand", 0),
    LAND(0x7F, "land", 0),
    IOR(0x80, "ior", 0),
    LOR(0x81, "lor", 0),
    IXOR(0x82, "ixor", 0),
    LXOR(0x83, "lxor", 0),
    IINC(0x84, "iinc", 2),
    I2L(0x85, "i2l", 0),
    I2F(0x86, "i2f", 0),
    I2D(0x87, "i2d", 0),
    L2I(0x88, "l2i", 0),
    L2F(0x89, "l2f", 0),
    L2D(0x8A, "l2d", 0),
    F2I(0x8B, "f2i", 0),
    F2L(0x8C, "f2l", 0),
    F2D(0x8D, "f2d", 0),
    D2I(0x8E, "d2i", 0),
    D2L(0x8F, "d2l", 0),
    D2F(0x90, "d2f", 0),
    I2B(0x91, "i2b", 0),
    I2C(0x92, "i2c", 0),
    I2S(0x93, "i2s", 0),
    LCMP(0x94, "lcmp", 0),
    FCMPL(0x95, "fcmpl", 0),
    FCMPG(0x96, "fcmpg", 0),
    DCMPL(0x97, "dcmpl", 0),
    DCMPG(0x98, "dcmpg", 0),
    IFEQ(0x99, "ifeq", 2),
    IFNE(0x9A, "ifne", 2),
    IFLT(0x9B, "iflt", 2),
    IFGE(0x9C, "ifge", 2),
    IFGT(0x9D, "ifgt", 2),
    IFLE(0x9E, "ifle", 2),
    IF_ICMPEQ(0x9F, "if_icmpeq", 2),
    IF_ICMPNE(0xA0, "if_icmpne", 2),
    IF_ICMPLT(0xA1, "if_icmplt", 2),
    IF_ICMPGE(0xA2, "if_icmpge", 2),
    IF_ICMPGT(0xA3, "if_icmpgt", 2),
    IF_ICMPLE(0xA4, "if_icmple", 2),
    IF_ACMPEQ(0xA5, "if_acmpeq", 2),
    IF_ACMPNE(0xA6, "if_acmpne", 2),
    GOTO(0xA7, "goto", 2),
    JSR(0xA8, "jsr", 2),
    RET(0xA9, "ret", 1),
    TABLESWITCH(0xAA, "tableswitch", -1),
    LOOKUPSWITCH(0xAB, "lookupswitch", -1),

    IRETURN(0xAC, "ireturn", 0),
    LRETURN(0xAD, "lreturn", 0),
    FRETURN(0xAE, "freturn", 0),
    DRETURN(0xAF, "dreturn", 0),
    ARETURN(0xB0, "areturn", 0),
    RETURN_(0xB1, "return", 0),

    GETSTATIC(0xB2, "getstatic", 2),
    PUTSTATIC(0xB3, "putstatic", 2),
    GETFIELD(0xB4, "getfield", 2),
    PUTFIELD(0xB5, "putfield", 2),
    INVOKEVIRTUAL(0xB6, "invokevirtual", 2),
    INVOKESPECIAL(0xB7, "invokespecial", 2),
    INVOKESTATIC(0xB8, "invokestatic", 2),
    INVOKEINTERFACE(0xB9, "invokeinterface", 4),
    INVOKEDYNAMIC(0xBA, "invokedynamic", 4),
    NEW(0xBB, "new", 2),
    NEWARRAY(0xBC, "newarray", 1),
    ANEWARRAY(0xBD, "anewarray", 2),
    ARRAYLENGTH(0xBE, "arraylength", 0),
    ATHROW(0xBF, "athrow", 0),
    CHECKCAST(0xC0, "checkcast", 2),
    INSTANCEOF(0xC1, "instanceof", 2),
    MONITORENTER(0xC2, "monitorenter", 0),
    MONITOREXIT(0xC3, "monitorexit", 0),
    WIDE(0xC4, "wide", -1), // variable-length
    MULTIANEWARRAY(0xC5, "multianewarray", 3),
    IFNULL(0xC6, "ifnull", 2),
    IFNONNULL(0xC7, "ifnonnull", 2),
    GOTO_W(0xC8, "goto_w", 4),
    JSR_W(0xC9, "jsr_w", 4),
    BREAKPOINT(0xCA, "breakpoint", 0),
    UNKNOWN(-1, "unknown", 0);

    private final int code;
    private final String mnemonic;
    private final int operandCount;

    Opcode(int code, String mnemonic, int operandCount) {
        this.code = code;
        this.mnemonic = mnemonic;
        this.operandCount = operandCount;
    }

    /**
     * Retrieves the Opcode enum constant corresponding to the specified bytecode value.
     *
     * @param code the bytecode value
     * @return the corresponding Opcode, or UNKNOWN if not found
     */
    public static Opcode fromCode(int code) {
        for (Opcode opcode : Opcode.values()) {
            if (opcode.code == code) {
                return opcode;
            }
        }
        return UNKNOWN;
    }
}
